fontgoggles/__init__.py
fontgoggles/_version.py
fontgoggles/project.py
fontgoggles/compile/__init__.py
fontgoggles/compile/compilerPool.py
fontgoggles/compile/dsCompiler.py
fontgoggles/compile/ttxCompiler.py
fontgoggles/compile/ufoCompiler.py
fontgoggles/compile/workServer.py
fontgoggles/font/__init__.py
fontgoggles/font/baseFont.py
fontgoggles/font/dsFont.py
fontgoggles/font/glyphDrawing.py
fontgoggles/font/otfFont.py
fontgoggles/font/ufoFont.py
fontgoggles/mac/__init__.py
fontgoggles/mac/aligningScrollView.py
fontgoggles/mac/appDelegate.py
fontgoggles/mac/document.py
fontgoggles/mac/drawing.py
fontgoggles/mac/featureTagGroup.py
fontgoggles/mac/fileObserver.py
fontgoggles/mac/fontList.py
fontgoggles/mac/libmakePathFromOutline.dylib
fontgoggles/mac/mainWindow.py
fontgoggles/mac/makePathFromOutline.py
fontgoggles/mac/misc.py
fontgoggles/mac/sliderGroup.py
fontgoggles/mac/tagView.py
fontgoggles/mac/unicodePicker.py
fontgoggles/mac/vanillaTabsOld.py
fontgoggles/misc/__init__.py
fontgoggles/misc/decorators.py
fontgoggles/misc/hbShape.py
fontgoggles/misc/opentypeTags.py
fontgoggles/misc/platform.py
fontgoggles/misc/properties.py
fontgoggles/misc/rectTree.py
fontgoggles/misc/segmenting.py
fontgoggles/misc/textInfo.py
fontgoggles/misc/unicodeNameList.py
coldtype_fontgoggles-1.8.4.7.dist-info/AUTHORS.txt
coldtype_fontgoggles-1.8.4.7.dist-info/LICENSE.txt
coldtype_fontgoggles-1.8.4.7.dist-info/METADATA
coldtype_fontgoggles-1.8.4.7.dist-info/WHEEL
coldtype_fontgoggles-1.8.4.7.dist-info/top_level.txt
coldtype_fontgoggles-1.8.4.7.dist-info/RECORD
