Metadata-Version: 2.1
Name: coldtype-fontgoggles
Version: 1.8.4.7
Summary: coldtype-fontgoggles is a PyPI-enabled version of the main library for the FontGoggles application.
Home-page: https://github.com/coldtype/fontgoggles
Author: Just van Rossum
Author-email: justvanrossum@gmail.com
Requires-Python: >=3.10
License-File: LICENSE.txt
License-File: AUTHORS.txt
Requires-Dist: blackrenderer >=0.6.0
Requires-Dist: fonttools >=4.53.1
Requires-Dist: uharfbuzz >=0.42.0
Requires-Dist: python-bidi ==0.4.2
Requires-Dist: unicodedata2 >=15.1.0
Provides-Extra: more-fonts
Requires-Dist: fonttools[lxml,type1,ufo,unicode,woff] >=4.53.1 ; extra == 'more-fonts'
Requires-Dist: ufo2ft ; extra == 'more-fonts'
Requires-Dist: numpy ; extra == 'more-fonts'
